Metadata-Version: 2.1
Name: argument-esa-model-weci2587
Version: 0.0.1
Summary: An ESA implementation in python.
Home-page: https://git.webis.de/args/args-topic-modeling/tree/master/src/python/esa
Author: Yamen Ajjour
Author-email: yajjour@hotmail.com
License: UNKNOWN
Platform: UNKNOWN
Classifier: Programming Language :: Python :: 3
Classifier: License :: OSI Approved :: MIT License
Classifier: Operating System :: OS Independent
Requires-Python: >=3.6
